<?xml version="1.0" encoding="utf-8"?>
	<annotation>
		<folder></folder>
		<filename>17_1_i_h_71168233___License Plate.jpg</filename>
		<source>
			<database>Unknown</database>
		</source>
		<path>17_1_i_h_71168233___License Plate.jpg</path>
		<size>
			<width>742</width>
			<height>400</height>
			<depth>3</depth>
		</size>
		<object>
			<name>5</name>
			<pose>Unspecified</pose>
			<truncated>0</truncated>
			<difficult>0</difficult>
			<bndbox>
				<xmin>338</xmin>
				<ymin>81</ymin>
				<xmax>435</xmax>
				<ymax>312</ymax>
			</bndbox>
		</object>
		<object>
			<name>3</name>
			<pose>Unspecified</pose>
			<truncated>0</truncated>
			<difficult>0</difficult>
			<bndbox>
				<xmin>432</xmin>
				<ymin>77</ymin>
				<xmax>527</xmax>
				<ymax>296</ymax>
			</bndbox>
		</object>
		<object>
			<name>3</name>
			<pose>Unspecified</pose>
			<truncated>0</truncated>
			<difficult>0</difficult>
			<bndbox>
				<xmin>609</xmin>
				<ymin>60</ymin>
				<xmax>694</xmax>
				<ymax>272</ymax>
			</bndbox>
		</object>
		<object>
			<name>V</name>
			<pose>Unspecified</pose>
			<truncated>0</truncated>
			<difficult>0</difficult>
			<bndbox>
				<xmin>90</xmin>
				<ymin>100</ymin>
				<xmax>188</xmax>
				<ymax>333</ymax>
			</bndbox>
		</object>
		<object>
			<name>M</name>
			<pose>Unspecified</pose>
			<truncated>0</truncated>
			<difficult>0</difficult>
			<bndbox>
				<xmin>203</xmin>
				<ymin>99</ymin>
				<xmax>301</xmax>
				<ymax>324</ymax>
			</bndbox>
		</object>
		<object>
			<name>7</name>
			<pose>Unspecified</pose>
			<truncated>0</truncated>
			<difficult>0</difficult>
			<bndbox>
				<xmin>521</xmin>
				<ymin>66</ymin>
				<xmax>610</xmax>
				<ymax>284</ymax>
			</bndbox>
		</object>
	</annotation>
