<annotation>
	<folder>pendding_17_20200912</folder>
	<filename>20200807210404_0211060777_S_R82.jpg</filename>
	<path>D:\CPOS AI\OD_OCR\pendding_17_20200912\20200807210404_0211060777_S_R82.jpg</path>
	<source>
		<database>Unknown</database>
	</source>
	<size>
		<width>101</width>
		<height>121</height>
		<depth>3</depth>
	</size>
	<segmented>0</segmented>
	<object>
		<name>R</name>
		<pose>Unspecified</pose>
		<truncated>0</truncated>
		<difficult>0</difficult>
		<bndbox>
			<xmin>29</xmin>
			<ymin>18</ymin>
			<xmax>52</xmax>
			<ymax>64</ymax>
		</bndbox>
	</object>
	<object>
		<name>8</name>
		<pose>Unspecified</pose>
		<truncated>0</truncated>
		<difficult>0</difficult>
		<bndbox>
			<xmin>13</xmin>
			<ymin>62</ymin>
			<xmax>33</xmax>
			<ymax>106</ymax>
		</bndbox>
	</object>
	<object>
		<name>2</name>
		<pose>Unspecified</pose>
		<truncated>0</truncated>
		<difficult>0</difficult>
		<bndbox>
			<xmin>32</xmin>
			<ymin>59</ymin>
			<xmax>51</xmax>
			<ymax>102</ymax>
		</bndbox>
	</object>
	<object>
		<name>V</name>
		<pose>Unspecified</pose>
		<truncated>0</truncated>
		<difficult>0</difficult>
		<bndbox>
			<xmin>50</xmin>
			<ymin>17</ymin>
			<xmax>71</xmax>
			<ymax>61</ymax>
		</bndbox>
	</object>
	<object>
		<name>8</name>
		<pose>Unspecified</pose>
		<truncated>0</truncated>
		<difficult>0</difficult>
		<bndbox>
			<xmin>50</xmin>
			<ymin>57</ymin>
			<xmax>70</xmax>
			<ymax>98</ymax>
		</bndbox>
	</object>
	<object>
		<name>5</name>
		<pose>Unspecified</pose>
		<truncated>0</truncated>
		<difficult>0</difficult>
		<bndbox>
			<xmin>67</xmin>
			<ymin>51</ymin>
			<xmax>88</xmax>
			<ymax>93</ymax>
		</bndbox>
	</object>
</annotation>
