<?xml version="1.0" encoding="utf-8"?>
	<annotation>
		<folder></folder>
		<filename>20200730101435_36317988_S_VV9542.jpg</filename>
		<source>
			<database>Unknown</database>
		</source>
		<path>20200730101435_36317988_S_VV9542.jpg</path>
		<size>
			<width>141</width>
			<height>100</height>
			<depth>3</depth>
		</size>
		<object>
			<name>4</name>
			<pose>Unspecified</pose>
			<truncated>0</truncated>
			<difficult>0</difficult>
			<bndbox>
				<xmin>106</xmin>
				<ymin>24</ymin>
				<xmax>123</xmax>
				<ymax>71</ymax>
			</bndbox>
		</object>
		<object>
			<name>2</name>
			<pose>Unspecified</pose>
			<truncated>0</truncated>
			<difficult>0</difficult>
			<bndbox>
				<xmin>122</xmin>
				<ymin>22</ymin>
				<xmax>139</xmax>
				<ymax>71</ymax>
			</bndbox>
		</object>
		<object>
			<name>V</name>
			<pose>Unspecified</pose>
			<truncated>0</truncated>
			<difficult>0</difficult>
			<bndbox>
				<xmin>19</xmin>
				<ymin>33</ymin>
				<xmax>43</xmax>
				<ymax>81</ymax>
			</bndbox>
		</object>
		<object>
			<name>V</name>
			<pose>Unspecified</pose>
			<truncated>0</truncated>
			<difficult>0</difficult>
			<bndbox>
				<xmin>39</xmin>
				<ymin>32</ymin>
				<xmax>63</xmax>
				<ymax>81</ymax>
			</bndbox>
		</object>
		<object>
			<name>9</name>
			<pose>Unspecified</pose>
			<truncated>0</truncated>
			<difficult>0</difficult>
			<bndbox>
				<xmin>66</xmin>
				<ymin>30</ymin>
				<xmax>89</xmax>
				<ymax>79</ymax>
			</bndbox>
		</object>
		<object>
			<name>5</name>
			<pose>Unspecified</pose>
			<truncated>0</truncated>
			<difficult>0</difficult>
			<bndbox>
				<xmin>86</xmin>
				<ymin>26</ymin>
				<xmax>106</xmax>
				<ymax>75</ymax>
			</bndbox>
		</object>
	</annotation>
