<?xml version="1.0" encoding="utf-8"?>
	<annotation>
		<folder></folder>
		<filename>20200624093610_0951801699_S.jpg_SHUKRAN.jpg</filename>
		<source>
			<database>Unknown</database>
		</source>
		<path>20200624093610_0951801699_S.jpg_SHUKRAN.jpg</path>
		<size>
			<width>114</width>
			<height>44</height>
			<depth>3</depth>
		</size>
		<object>
			<name>S</name>
			<pose>Unspecified</pose>
			<truncated>0</truncated>
			<difficult>0</difficult>
			<bndbox>
				<xmin>24</xmin>
				<ymin>14</ymin>
				<xmax>35</xmax>
				<ymax>40</ymax>
			</bndbox>
		</object>
		<object>
			<name>H</name>
			<pose>Unspecified</pose>
			<truncated>0</truncated>
			<difficult>0</difficult>
			<bndbox>
				<xmin>35</xmin>
				<ymin>14</ymin>
				<xmax>46</xmax>
				<ymax>40</ymax>
			</bndbox>
		</object>
		<object>
			<name>U</name>
			<pose>Unspecified</pose>
			<truncated>0</truncated>
			<difficult>0</difficult>
			<bndbox>
				<xmin>47</xmin>
				<ymin>16</ymin>
				<xmax>58</xmax>
				<ymax>40</ymax>
			</bndbox>
		</object>
		<object>
			<name>K</name>
			<pose>Unspecified</pose>
			<truncated>0</truncated>
			<difficult>0</difficult>
			<bndbox>
				<xmin>56</xmin>
				<ymin>16</ymin>
				<xmax>67</xmax>
				<ymax>40</ymax>
			</bndbox>
		</object>
		<object>
			<name>R</name>
			<pose>Unspecified</pose>
			<truncated>0</truncated>
			<difficult>0</difficult>
			<bndbox>
				<xmin>68</xmin>
				<ymin>16</ymin>
				<xmax>78</xmax>
				<ymax>40</ymax>
			</bndbox>
		</object>
		<object>
			<name>A</name>
			<pose>Unspecified</pose>
			<truncated>0</truncated>
			<difficult>0</difficult>
			<bndbox>
				<xmin>79</xmin>
				<ymin>14</ymin>
				<xmax>89</xmax>
				<ymax>42</ymax>
			</bndbox>
		</object>
		<object>
			<name>N</name>
			<pose>Unspecified</pose>
			<truncated>0</truncated>
			<difficult>0</difficult>
			<bndbox>
				<xmin>89</xmin>
				<ymin>14</ymin>
				<xmax>99</xmax>
				<ymax>41</ymax>
			</bndbox>
		</object>
	</annotation>
