<?xml version="1.0" encoding="utf-8"?>
	<annotation>
		<folder></folder>
		<filename>20200809142846_4019096053_TZ8185.jpg</filename>
		<source>
			<database>Unknown</database>
		</source>
		<path>20200809142846_4019096053_TZ8185.jpg</path>
		<size>
			<width>200</width>
			<height>129</height>
			<depth>3</depth>
		</size>
		<object>
			<name>T</name>
			<pose>Unspecified</pose>
			<truncated>0</truncated>
			<difficult>0</difficult>
			<bndbox>
				<xmin>67</xmin>
				<ymin>21</ymin>
				<xmax>108</xmax>
				<ymax>74</ymax>
			</bndbox>
		</object>
		<object>
			<name>Z</name>
			<pose>Unspecified</pose>
			<truncated>0</truncated>
			<difficult>0</difficult>
			<bndbox>
				<xmin>101</xmin>
				<ymin>20</ymin>
				<xmax>136</xmax>
				<ymax>71</ymax>
			</bndbox>
		</object>
		<object>
			<name>8</name>
			<pose>Unspecified</pose>
			<truncated>0</truncated>
			<difficult>0</difficult>
			<bndbox>
				<xmin>96</xmin>
				<ymin>66</ymin>
				<xmax>134</xmax>
				<ymax>117</ymax>
			</bndbox>
		</object>
		<object>
			<name>5</name>
			<pose>Unspecified</pose>
			<truncated>0</truncated>
			<difficult>0</difficult>
			<bndbox>
				<xmin>129</xmin>
				<ymin>63</ymin>
				<xmax>164</xmax>
				<ymax>115</ymax>
			</bndbox>
		</object>
		<object>
			<name>8</name>
			<pose>Unspecified</pose>
			<truncated>0</truncated>
			<difficult>0</difficult>
			<bndbox>
				<xmin>35</xmin>
				<ymin>68</ymin>
				<xmax>76</xmax>
				<ymax>124</ymax>
			</bndbox>
		</object>
		<object>
			<name>1</name>
			<pose>Unspecified</pose>
			<truncated>0</truncated>
			<difficult>0</difficult>
			<bndbox>
				<xmin>72</xmin>
				<ymin>69</ymin>
				<xmax>99</xmax>
				<ymax>119</ymax>
			</bndbox>
		</object>
	</annotation>
