<?xml version="1.0" encoding="utf-8"?>
	<annotation>
		<folder></folder>
		<filename>20200806150728_0823976953_S_WV5808.jpg</filename>
		<source>
			<database>Unknown</database>
		</source>
		<path>20200806150728_0823976953_S_WV5808.jpg</path>
		<size>
			<width>123</width>
			<height>113</height>
			<depth>3</depth>
		</size>
		<object>
			<name>W</name>
			<pose>Unspecified</pose>
			<truncated>0</truncated>
			<difficult>0</difficult>
			<bndbox>
				<xmin>39</xmin>
				<ymin>13</ymin>
				<xmax>62</xmax>
				<ymax>58</ymax>
			</bndbox>
		</object>
		<object>
			<name>V</name>
			<pose>Unspecified</pose>
			<truncated>0</truncated>
			<difficult>0</difficult>
			<bndbox>
				<xmin>60</xmin>
				<ymin>12</ymin>
				<xmax>83</xmax>
				<ymax>55</ymax>
			</bndbox>
		</object>
		<object>
			<name>0</name>
			<pose>Unspecified</pose>
			<truncated>0</truncated>
			<difficult>0</difficult>
			<bndbox>
				<xmin>60</xmin>
				<ymin>49</ymin>
				<xmax>83</xmax>
				<ymax>95</ymax>
			</bndbox>
		</object>
		<object>
			<name>8</name>
			<pose>Unspecified</pose>
			<truncated>0</truncated>
			<difficult>0</difficult>
			<bndbox>
				<xmin>81</xmin>
				<ymin>46</ymin>
				<xmax>103</xmax>
				<ymax>92</ymax>
			</bndbox>
		</object>
		<object>
			<name>5</name>
			<pose>Unspecified</pose>
			<truncated>0</truncated>
			<difficult>0</difficult>
			<bndbox>
				<xmin>17</xmin>
				<ymin>53</ymin>
				<xmax>42</xmax>
				<ymax>100</ymax>
			</bndbox>
		</object>
		<object>
			<name>8</name>
			<pose>Unspecified</pose>
			<truncated>0</truncated>
			<difficult>0</difficult>
			<bndbox>
				<xmin>39</xmin>
				<ymin>53</ymin>
				<xmax>63</xmax>
				<ymax>96</ymax>
			</bndbox>
		</object>
	</annotation>
