<annotation>
	<folder>pendding_20200903_21_27_33</folder>
	<filename>20200805092420_05691835_E573.jpg</filename>
	<path>D:\CPOS AI\OD_OCR\pendding_20200903_21_27_33\20200805092420_05691835_E573.jpg</path>
	<source>
		<database>Unknown</database>
	</source>
	<size>
		<width>211</width>
		<height>158</height>
		<depth>3</depth>
	</size>
	<segmented>0</segmented>
	<object>
		<name>E</name>
		<pose>Unspecified</pose>
		<truncated>0</truncated>
		<difficult>0</difficult>
		<bndbox>
			<xmin>107</xmin>
			<ymin>16</ymin>
			<xmax>149</xmax>
			<ymax>77</ymax>
		</bndbox>
	</object>
	<object>
		<name>3</name>
		<pose>Unspecified</pose>
		<truncated>0</truncated>
		<difficult>0</difficult>
		<bndbox>
			<xmin>107</xmin>
			<ymin>69</ymin>
			<xmax>146</xmax>
			<ymax>131</ymax>
		</bndbox>
	</object>
	<object>
		<name>5</name>
		<pose>Unspecified</pose>
		<truncated>0</truncated>
		<difficult>0</difficult>
		<bndbox>
			<xmin>24</xmin>
			<ymin>77</ymin>
			<xmax>68</xmax>
			<ymax>136</ymax>
		</bndbox>
	</object>
	<object>
		<name>7</name>
		<pose>Unspecified</pose>
		<truncated>0</truncated>
		<difficult>0</difficult>
		<bndbox>
			<xmin>68</xmin>
			<ymin>74</ymin>
			<xmax>109</xmax>
			<ymax>131</ymax>
		</bndbox>
	</object>
	<object>
		<name>D</name>
		<pose>Unspecified</pose>
		<truncated>0</truncated>
		<difficult>0</difficult>
		<bndbox>
			<xmin>66</xmin>
			<ymin>18</ymin>
			<xmax>108</xmax>
			<ymax>78</ymax>
		</bndbox>
	</object>
	<object>
		<name>9</name>
		<pose>Unspecified</pose>
		<truncated>0</truncated>
		<difficult>0</difficult>
		<bndbox>
			<xmin>145</xmin>
			<ymin>62</ymin>
			<xmax>186</xmax>
			<ymax>122</ymax>
		</bndbox>
	</object>
</annotation>
