<?xml version="1.0" encoding="utf-8"?>
	<annotation>
		<folder></folder>
		<filename>20200819215041_0454573889_S_UA3975.jpg</filename>
		<source>
			<database>Unknown</database>
		</source>
		<path>20200819215041_0454573889_S_UA3975.jpg</path>
		<size>
			<width>176</width>
			<height>77</height>
			<depth>3</depth>
		</size>
		<object>
			<name>5</name>
			<pose>Unspecified</pose>
			<truncated>0</truncated>
			<difficult>0</difficult>
			<bndbox>
				<xmin>138</xmin>
				<ymin>9</ymin>
				<xmax>159</xmax>
				<ymax>53</ymax>
			</bndbox>
		</object>
		<object>
			<name>3</name>
			<pose>Unspecified</pose>
			<truncated>0</truncated>
			<difficult>0</difficult>
			<bndbox>
				<xmin>78</xmin>
				<ymin>13</ymin>
				<xmax>101</xmax>
				<ymax>63</ymax>
			</bndbox>
		</object>
		<object>
			<name>9</name>
			<pose>Unspecified</pose>
			<truncated>0</truncated>
			<difficult>0</difficult>
			<bndbox>
				<xmin>100</xmin>
				<ymin>13</ymin>
				<xmax>122</xmax>
				<ymax>59</ymax>
			</bndbox>
		</object>
		<object>
			<name>7</name>
			<pose>Unspecified</pose>
			<truncated>0</truncated>
			<difficult>0</difficult>
			<bndbox>
				<xmin>119</xmin>
				<ymin>12</ymin>
				<xmax>142</xmax>
				<ymax>56</ymax>
			</bndbox>
		</object>
		<object>
			<name>A</name>
			<pose>Unspecified</pose>
			<truncated>0</truncated>
			<difficult>0</difficult>
			<bndbox>
				<xmin>49</xmin>
				<ymin>16</ymin>
				<xmax>73</xmax>
				<ymax>69</ymax>
			</bndbox>
		</object>
		<object>
			<name>U</name>
			<pose>Unspecified</pose>
			<truncated>0</truncated>
			<difficult>0</difficult>
			<bndbox>
				<xmin>24</xmin>
				<ymin>19</ymin>
				<xmax>51</xmax>
				<ymax>70</ymax>
			</bndbox>
		</object>
	</annotation>
